LICENSE
README.md
joy.py
setup.py
python_joy.egg-info/PKG-INFO
python_joy.egg-info/SOURCES.txt
python_joy.egg-info/dependency_links.txt
python_joy.egg-info/top_level.txt
tests/test_joy.py