Metadata-Version: 2.1
Name: python-joy
Version: 0.4.0
Summary: Tiny creative coding library in Python
Home-page: https://github.com/anandology/joy
Author: Anand Chitipothu
Author-email: anandology@gmail.com
License: MIT
Platform: any
License-File: LICENSE
